KingClass/__init__.py
KingClass/functions.py
PawnClass/__init__.py
PawnClass/functions.py
cherkersOnline-1.0.data/scripts/exec
cherkersOnline-1.0.dist-info/METADATA
cherkersOnline-1.0.dist-info/WHEEL
cherkersOnline-1.0.dist-info/top_level.txt
cherkersOnline-1.0.dist-info/RECORD
