Metadata-Version: 2.1
Name: cherkersOnline
Version: 1.0
Summary: An online checkers game
Home-page: https://github.com/Surya-nara0123/Checkers-Online
Author: Surya Narayanan
Author-email: surya.nara0123@gmail.com
Classifier: Programming Language :: Python :: 3.10
Classifier: License :: OSI Approved :: MIT License
Classifier: Operating System :: OS Independent
